<?xml version="1.0" encoding="UTF-8" standalone="yes"?>
<ns0:RetrieveValueSetResponse xmlns:ns0="urn:ihe:iti:svs:2008" xmlns:xsi="http://www.w3.org/2001/XMLSchema-instance">
    <ns0:ValueSet ID="2.16.840.1.113762.1.4.1287.10" displayName="食道或賁門之惡性腫瘤" version="Latest">
        <ns0:ConceptList>
            <ns0:Concept code="C15.3" codeSystem="2.16.840.1.113883.6.90" codeSystemName="ICD10CM" codeSystemVersion="2025" displayName="Malignant neoplasm of upper third of esophagus"/>
            <ns0:Concept code="C15.4" codeSystem="2.16.840.1.113883.6.90" codeSystemName="ICD10CM" codeSystemVersion="2025" displayName="Malignant neoplasm of middle third of esophagus"/>
            <ns0:Concept code="C15.5" codeSystem="2.16.840.1.113883.6.90" codeSystemName="ICD10CM" codeSystemVersion="2025" displayName="Malignant neoplasm of lower third of esophagus"/>
            <ns0:Concept code="C15.8" codeSystem="2.16.840.1.113883.6.90" codeSystemName="ICD10CM" codeSystemVersion="2025" displayName="Malignant neoplasm of overlapping sites of esophagus"/>
            <ns0:Concept code="C15.9" codeSystem="2.16.840.1.113883.6.90" codeSystemName="ICD10CM" codeSystemVersion="2025" displayName="Malignant neoplasm of esophagus, unspecified"/>
            <ns0:Concept code="C16" codeSystem="2.16.840.1.113883.6.90" codeSystemName="ICD10CM" codeSystemVersion="2025" displayName="Malignant neoplasm of stomach"/>
            <ns0:Concept code="C16.0" codeSystem="2.16.840.1.113883.6.90" codeSystemName="ICD10CM" codeSystemVersion="2025" displayName="Malignant neoplasm of cardia"/>
            <ns0:Concept code="C16.1" codeSystem="2.16.840.1.113883.6.90" codeSystemName="ICD10CM" codeSystemVersion="2025" displayName="Malignant neoplasm of fundus of stomach"/>
            <ns0:Concept code="C16.2" codeSystem="2.16.840.1.113883.6.90" codeSystemName="ICD10CM" codeSystemVersion="2025" displayName="Malignant neoplasm of body of stomach"/>
            <ns0:Concept code="C16.3" codeSystem="2.16.840.1.113883.6.90" codeSystemName="ICD10CM" codeSystemVersion="2025" displayName="Malignant neoplasm of pyloric antrum"/>
            <ns0:Concept code="C16.4" codeSystem="2.16.840.1.113883.6.90" codeSystemName="ICD10CM" codeSystemVersion="2025" displayName="Malignant neoplasm of pylorus"/>
            <ns0:Concept code="C16.5" codeSystem="2.16.840.1.113883.6.90" codeSystemName="ICD10CM" codeSystemVersion="2025" displayName="Malignant neoplasm of lesser curvature of stomach, unspecified"/>
            <ns0:Concept code="C16.6" codeSystem="2.16.840.1.113883.6.90" codeSystemName="ICD10CM" codeSystemVersion="2025" displayName="Malignant neoplasm of greater curvature of stomach, unspecified"/>
            <ns0:Concept code="C16.8" codeSystem="2.16.840.1.113883.6.90" codeSystemName="ICD10CM" codeSystemVersion="2025" displayName="Malignant neoplasm of overlapping sites of stomach"/>
            <ns0:Concept code="C16.9" codeSystem="2.16.840.1.113883.6.90" codeSystemName="ICD10CM" codeSystemVersion="2025" displayName="Malignant neoplasm of stomach, unspecified"/>
            <ns0:Concept code="C78.89" codeSystem="2.16.840.1.113883.6.90" codeSystemName="ICD10CM" codeSystemVersion="2025" displayName="Secondary malignant neoplasm of other digestive organs"/>
        </ns0:ConceptList>
    </ns0:ValueSet>
</ns0:RetrieveValueSetResponse>
