<?xml version="1.0" encoding="UTF-8" standalone="yes"?>
<ns0:RetrieveValueSetResponse xmlns:ns0="urn:ihe:iti:svs:2008" xmlns:xsi="http://www.w3.org/2001/XMLSchema-instance">
    <ns0:ValueSet ID="2.16.840.1.113762.1.4.1287.31" displayName="33113B 經頸靜脈肝內門脈系統靜脈分流術Transjugular Intrahepatic Portosystemic Shunt" version="Latest">
        <ns0:ConceptList>
            <ns0:Concept code="E87.0" codeSystem="2.16.840.1.113883.6.90" codeSystemName="ICD10CM" codeSystemVersion="2025" displayName="Hyperosmolality and hypernatremia"/>
            <ns0:Concept code="E87.1" codeSystem="2.16.840.1.113883.6.90" codeSystemName="ICD10CM" codeSystemVersion="2025" displayName="Hypo-osmolality and hyponatremia"/>
            <ns0:Concept code="E87.5" codeSystem="2.16.840.1.113883.6.90" codeSystemName="ICD10CM" codeSystemVersion="2025" displayName="Hyperkalemia"/>
            <ns0:Concept code="E87.6" codeSystem="2.16.840.1.113883.6.90" codeSystemName="ICD10CM" codeSystemVersion="2025" displayName="Hypokalemia"/>
            <ns0:Concept code="E87.8" codeSystem="2.16.840.1.113883.6.90" codeSystemName="ICD10CM" codeSystemVersion="2025" displayName="Other disorders of electrolyte and fluid balance, not elsewhere classified"/>
            <ns0:Concept code="I82.0" codeSystem="2.16.840.1.113883.6.90" codeSystemName="ICD10CM" codeSystemVersion="2025" displayName="Budd-Chiari syndrome"/>
            <ns0:Concept code="I85.01" codeSystem="2.16.840.1.113883.6.90" codeSystemName="ICD10CM" codeSystemVersion="2025" displayName="Esophageal varices with bleeding"/>
            <ns0:Concept code="I85.11" codeSystem="2.16.840.1.113883.6.90" codeSystemName="ICD10CM" codeSystemVersion="2025" displayName="Secondary esophageal varices with bleeding"/>
            <ns0:Concept code="I86.4" codeSystem="2.16.840.1.113883.6.90" codeSystemName="ICD10CM" codeSystemVersion="2025" displayName="Gastric varices"/>
            <ns0:Concept code="K70.31" codeSystem="2.16.840.1.113883.6.90" codeSystemName="ICD10CM" codeSystemVersion="2025" displayName="Alcoholic cirrhosis of liver with ascites"/>
            <ns0:Concept code="K74.60" codeSystem="2.16.840.1.113883.6.90" codeSystemName="ICD10CM" codeSystemVersion="2025" displayName="Unspecified cirrhosis of liver"/>
            <ns0:Concept code="K92.2" codeSystem="2.16.840.1.113883.6.90" codeSystemName="ICD10CM" codeSystemVersion="2025" displayName="Gastrointestinal hemorrhage, unspecified"/>
            <ns0:Concept code="N18.5" codeSystem="2.16.840.1.113883.6.90" codeSystemName="ICD10CM" codeSystemVersion="2025" displayName="Chronic kidney disease, stage 5"/>
            <ns0:Concept code="N18.6" codeSystem="2.16.840.1.113883.6.90" codeSystemName="ICD10CM" codeSystemVersion="2025" displayName="End stage renal disease"/>
            <ns0:Concept code="R18.8" codeSystem="2.16.840.1.113883.6.90" codeSystemName="ICD10CM" codeSystemVersion="2025" displayName="Other ascites"/>
        </ns0:ConceptList>
    </ns0:ValueSet>
</ns0:RetrieveValueSetResponse>
